sofizpay/__init__.py
sofizpay/client.py
sofizpay/exceptions.py
sofizpay/payments.py
sofizpay/transactions.py
sofizpay/utils.py
sofizpay_sdk_python-1.0.2.dist-info/licenses/LICENSE
sofizpay_sdk_python-1.0.2.dist-info/METADATA
sofizpay_sdk_python-1.0.2.dist-info/WHEEL
sofizpay_sdk_python-1.0.2.dist-info/top_level.txt
sofizpay_sdk_python-1.0.2.dist-info/RECORD
