Metadata-Version: 2.4
Name: sofizpay-sdk-python
Version: 1.0.2
Summary: Professional Python SDK for SofizPay payments using Stellar blockchain
Home-page: https://github.com/kenandarabeh/sofizpay-sdk-python
Author: SofizPay Team
Author-email: SofizPay Team <support@sofizpay.com>
Maintainer-email: SofizPay Team <support@sofizpay.com>
License: MIT
Project-URL: Homepage, https://sofizpay.com
Project-URL: Documentation, https://github.com/kenandarabeh/sofizpay-sdk-python#readme
Project-URL: Repository, https://github.com/kenandarabeh/sofizpay-sdk-python
Project-URL: Bug Reports, https://github.com/kenandarabeh/sofizpay-sdk-python/issues
Project-URL: Changelog, https://github.com/kenandarabeh/sofizpay-sdk-python/blob/main/CHANGELOG.md
Keywords: stellar,payment,blockchain,cryptocurrency,DZT,sofizpay,fintech
Classifier: Development Status :: 5 - Production/Stable
Classifier: Intended Audience :: Developers
Classifier: License :: OSI Approved :: MIT License
Classifier: Operating System :: OS Independent
Classifier: Programming Language :: Python :: 3
Classifier: Programming Language :: Python :: 3.8
Classifier: Programming Language :: Python :: 3.9
Classifier: Programming Language :: Python :: 3.10
Classifier: Programming Language :: Python :: 3.11
Classifier: Programming Language :: Python :: 3.12
Classifier: Topic :: Office/Business :: Financial
Classifier: Topic :: Software Development :: Libraries :: Python Modules
Classifier: Topic :: Internet :: WWW/HTTP
Classifier: Typing :: Typed
Requires-Python: >=3.8
License-File: LICENSE
Requires-Dist: stellar-sdk>=8.0.0
Requires-Dist: requests>=2.25.0
Requires-Dist: asyncio-throttle>=1.0.0
Requires-Dist: websockets>=10.0
Requires-Dist: cryptography>=3.4.0
Requires-Dist: pycryptodome>=3.15.0
Provides-Extra: dev
Requires-Dist: pytest>=7.0.0; extra == "dev"
Requires-Dist: pytest-asyncio>=0.21.0; extra == "dev"
Requires-Dist: pytest-mock>=3.10.0; extra == "dev"
Requires-Dist: black>=23.0.0; extra == "dev"
Requires-Dist: flake8>=6.0.0; extra == "dev"
Requires-Dist: mypy>=1.0.0; extra == "dev"
Requires-Dist: isort>=5.12.0; extra == "dev"
Requires-Dist: coverage>=7.0.0; extra == "dev"
Dynamic: author
Dynamic: home-page
Dynamic: license-file
Dynamic: requires-python
